[
  {
    "id": "2ed93f1c-7b58-4182-9791-9ad7421f74ad",
    "company_id": "22e15616-ddab-463d-8c8e-cd89d0fbcf33",
    "division_number": 6,
    "division_name": "Finish Carpentry",
    "task_code": "06.C",
    "task_name": "Hanging Interior Pre-Hung Doors",
    "min_competency_to_solo": "mastery",
    "is_high_hazard": false,
    "estimated_hours": 4.0,
    "training_video_url": "https://r2.kineticflow.app/training/06.c.mp4",
    "created_at": "2024-08-01T12:00:00Z",
    "updated_at": "2025-12-14T12:00:00Z"
  },
  {
    "id": "ed9c334b-f43b-4004-a495-a61b36585052",
    "company_id": "22e15616-ddab-463d-8c8e-cd89d0fbcf33",
    "division_number": 6,
    "division_name": "Finish Carpentry",
    "task_code": "06.T",
    "task_name": "Installing Baseboard Trim",
    "min_competency_to_solo": "competent",
    "is_high_hazard": false,
    "estimated_hours": 3.5,
    "training_video_url": "https://r2.kineticflow.app/training/06.t.mp4",
    "created_at": "2024-08-01T12:00:00Z",
    "updated_at": "2025-12-14T12:00:00Z"
  },
  {
    "id": "ea44e3fa-7f46-4f4f-8d14-510bfadd58b6",
    "company_id": "22e15616-ddab-463d-8c8e-cd89d0fbcf33",
    "division_number": 9,
    "division_name": "Painting",
    "task_code": "09.A",
    "task_name": "Interior Wall Painting - 2 Coat",
    "min_competency_to_solo": "exposure",
    "is_high_hazard": false,
    "estimated_hours": 6.0,
    "training_video_url": "https://r2.kineticflow.app/training/09.a.mp4",
    "created_at": "2024-08-01T12:00:00Z",
    "updated_at": "2025-12-14T12:00:00Z"
  },
  {
    "id": "9dd46ed9-585b-4a99-8f2a-731ddc805f82",
    "company_id": "22e15616-ddab-463d-8c8e-cd89d0fbcf33",
    "division_number": 9,
    "division_name": "Painting",
    "task_code": "09.D",
    "task_name": "Drywall Patch & Texture Match",
    "min_competency_to_solo": "competent",
    "is_high_hazard": false,
    "estimated_hours": 2.5,
    "training_video_url": "https://r2.kineticflow.app/training/09.d.mp4",
    "created_at": "2024-08-01T12:00:00Z",
    "updated_at": "2025-12-14T12:00:00Z"
  },
  {
    "id": "242a61ae-84d0-4725-a46f-8b88630f18f7",
    "company_id": "22e15616-ddab-463d-8c8e-cd89d0fbcf33",
    "division_number": 22,
    "division_name": "Plumbing",
    "task_code": "22.R",
    "task_name": "Rough-In Supply & Drain Lines",
    "min_competency_to_solo": "mastery",
    "is_high_hazard": true,
    "estimated_hours": 8.0,
    "training_video_url": "https://r2.kineticflow.app/training/22.r.mp4",
    "created_at": "2024-08-01T12:00:00Z",
    "updated_at": "2025-12-14T12:00:00Z"
  },
  {
    "id": "ee54b45c-92ec-4d89-8543-6b10e7fbb961",
    "company_id": "22e15616-ddab-463d-8c8e-cd89d0fbcf33",
    "division_number": 22,
    "division_name": "Plumbing",
    "task_code": "22.F",
    "task_name": "Fixture Set - Sink & Faucet",
    "min_competency_to_solo": "competent",
    "is_high_hazard": false,
    "estimated_hours": 2.0,
    "training_video_url": "https://r2.kineticflow.app/training/22.f.mp4",
    "created_at": "2024-08-01T12:00:00Z",
    "updated_at": "2025-12-14T12:00:00Z"
  },
  {
    "id": "4c837749-e737-45b8-9bfc-880049f09b71",
    "company_id": "22e15616-ddab-463d-8c8e-cd89d0fbcf33",
    "division_number": 23,
    "division_name": "HVAC",
    "task_code": "23.A",
    "task_name": "Air Handler Install",
    "min_competency_to_solo": "mastery",
    "is_high_hazard": true,
    "estimated_hours": 10.0,
    "training_video_url": "https://r2.kineticflow.app/training/23.a.mp4",
    "created_at": "2024-08-01T12:00:00Z",
    "updated_at": "2025-12-14T12:00:00Z"
  },
  {
    "id": "2a884123-b4f4-4cd3-a0a6-6a7c5eb0fd0e",
    "company_id": "22e15616-ddab-463d-8c8e-cd89d0fbcf33",
    "division_number": 23,
    "division_name": "HVAC",
    "task_code": "23.D",
    "task_name": "Ductwork Run & Seal",
    "min_competency_to_solo": "competent",
    "is_high_hazard": true,
    "estimated_hours": 6.5,
    "training_video_url": "https://r2.kineticflow.app/training/23.d.mp4",
    "created_at": "2024-08-01T12:00:00Z",
    "updated_at": "2025-12-14T12:00:00Z"
  },
  {
    "id": "bcf333b0-2a1c-4fee-8a54-b0591dd649a5",
    "company_id": "22e15616-ddab-463d-8c8e-cd89d0fbcf33",
    "division_number": 26,
    "division_name": "Electrical",
    "task_code": "26.P",
    "task_name": "200A Panel Replacement",
    "min_competency_to_solo": "mastery",
    "is_high_hazard": true,
    "estimated_hours": 9.0,
    "training_video_url": "https://r2.kineticflow.app/training/26.p.mp4",
    "created_at": "2024-08-01T12:00:00Z",
    "updated_at": "2025-12-14T12:00:00Z"
  },
  {
    "id": "3345df1d-4970-4b23-a3e5-ae63ffca0d46",
    "company_id": "22e15616-ddab-463d-8c8e-cd89d0fbcf33",
    "division_number": 26,
    "division_name": "Electrical",
    "task_code": "26.W",
    "task_name": "Rough-In Wiring - Residential Branch Circuits",
    "min_competency_to_solo": "competent",
    "is_high_hazard": true,
    "estimated_hours": 7.0,
    "training_video_url": "https://r2.kineticflow.app/training/26.w.mp4",
    "created_at": "2024-08-01T12:00:00Z",
    "updated_at": "2025-12-14T12:00:00Z"
  },
  {
    "id": "734b3c28-f789-472f-a55b-8edb454025ee",
    "company_id": "22e15616-ddab-463d-8c8e-cd89d0fbcf33",
    "division_number": 26,
    "division_name": "Electrical",
    "task_code": "26.S",
    "task_name": "Switch & Receptacle Trim-Out",
    "min_competency_to_solo": "exposure",
    "is_high_hazard": false,
    "estimated_hours": 3.0,
    "training_video_url": "https://r2.kineticflow.app/training/26.s.mp4",
    "created_at": "2024-08-01T12:00:00Z",
    "updated_at": "2025-12-14T12:00:00Z"
  },
  {
    "id": "f9f8d27f-414d-4b0b-9d3f-6326ff6fb839",
    "company_id": "22e15616-ddab-463d-8c8e-cd89d0fbcf33",
    "division_number": 9,
    "division_name": "Painting",
    "task_code": "09.C",
    "task_name": "Exterior Caulking & Prep",
    "min_competency_to_solo": "student",
    "is_high_hazard": false,
    "estimated_hours": 2.0,
    "training_video_url": "https://r2.kineticflow.app/training/09.c.mp4",
    "created_at": "2024-08-01T12:00:00Z",
    "updated_at": "2025-12-14T12:00:00Z"
  }
]
